git_rg.py
git_rg-0.2.1.dist-info/METADATA
git_rg-0.2.1.dist-info/WHEEL
git_rg-0.2.1.dist-info/entry_points.txt
git_rg-0.2.1.dist-info/top_level.txt
git_rg-0.2.1.dist-info/RECORD
