Metadata-Version: 2.1
Name: git-rg
Version: 0.2.1
Summary: Git Recursive Grep
Author: s3rgeym
License: MIT
